musr2py.cpython-36m-x86_64-linux-gnu.so
musr2py-0.0.2.dist-info/LICENSE.txt
musr2py-0.0.2.dist-info/WHEEL
musr2py-0.0.2.dist-info/top_level.txt
musr2py-0.0.2.dist-info/RECORD
musr2py-0.0.2.dist-info/METADATA
