Metadata-Version: 2.1
Name: musr2py
Version: 0.0.2
Summary: Read PSI bin with Python
Author: Pietro Bonfa
Author-email: bonfus@gmail.com
License: GPL
Classifier: Development Status :: 3 - Alpha
Classifier: Environment :: Console
Classifier: Intended Audience :: Developers
Classifier: Intended Audience :: Science/Research
Classifier: License :: OSI Approved :: GNU General Public License v3 or later (GPLv3+)
Classifier: Operating System :: MacOS :: MacOS X
Classifier: Operating System :: Microsoft :: Windows
Classifier: Operating System :: POSIX
Classifier: Topic :: Scientific/Engineering :: Physics
License-File: LICENSE.txt
